{
  "segments": [
    {
      "id": "line_000",
      "start": 0.0,
      "end": 13.06,
      "label": "",
      "text": "소음 가득한 거리 위로"
    },
    {
      "id": "line_001",
      "start": 13.18,
      "end": 13.78,
      "label": "",
      "text": "흐릿한 네온사인 불빛"
    },
    {
      "id": "line_002",
      "start": 13.78,
      "end": 14.22,
      "label": "",
      "text": "스쳐 가는 무표정한 얼굴들"
    },
    {
      "id": "line_003",
      "start": 14.34,
      "end": 24.94,
      "label": "",
      "text": "어지러운 밤의 멜로디"
    }
  ],
  "duration": 24.94,
  "updated_at": 1758732197
}